setup.py
binom_probability/Binomialdistribution.py
binom_probability/Gaussiandistribution.py
binom_probability/Generaldistribution.py
binom_probability/__init__.py
binom_probability.egg-info/PKG-INFO
binom_probability.egg-info/SOURCES.txt
binom_probability.egg-info/dependency_links.txt
binom_probability.egg-info/not-zip-safe
binom_probability.egg-info/top_level.txt