Metadata-Version: 1.0
Name: binom-probability
Version: 1.3
Summary: Gaussian distributions and Binomial distribution
Home-page: UNKNOWN
Author: bantuaparna
Author-email: bantuaparna@gmail.com
License: UNKNOWN
Platform: UNKNOWN
